sopel_spongemock/__init__.py
sopel_spongemock/util.py
sopel_spongemock-1.2.0.dist-info/COPYING
sopel_spongemock-1.2.0.dist-info/METADATA
sopel_spongemock-1.2.0.dist-info/WHEEL
sopel_spongemock-1.2.0.dist-info/entry_points.txt
sopel_spongemock-1.2.0.dist-info/top_level.txt
sopel_spongemock-1.2.0.dist-info/RECORD
