Metadata-Version: 2.1
Name: sopel-spongemock
Version: 1.2.0
Summary: Sopel plugin to generate "Spongemock" text (based on *that* SpongeBob meme)
Author-email: dgw <dgw@technobabbl.es>
License: EFL-2.0
Project-URL: Homepage, https://github.com/dgw/sopel-spongemock
Project-URL: Bug Tracker, https://github.com/dgw/sopel-spongemock/issues
Keywords: sopel,plugin,bot,irc
Platform: Linux x86, x86-64
Classifier: Intended Audience :: Developers
Classifier: Intended Audience :: System Administrators
Classifier: License :: Eiffel Forum License (EFL)
Classifier: License :: OSI Approved :: Eiffel Forum License
Classifier: Programming Language :: Python :: 3 :: Only
Classifier: Topic :: Communications :: Chat :: Internet Relay Chat
Requires-Python: <4,>=3.8
License-File: COPYING
Requires-Dist: sopel>=8.0
Provides-Extra: lib
Requires-Dist: spongemock; extra == "lib"
Provides-Extra: ud2
Requires-Dist: unicodedata2; extra == "ud2"
